giql/__init__.py
giql/cli.py
giql/constants.py
giql/dialect.py
giql/engine.py
giql/expressions.py
giql/protocols.py
giql/range_parser.py
giql/schema.py
giql/transformer.py
giql/generators/__init__.py
giql/generators/base.py
giql/generators/duckdb.py
giql/generators/sqlite.py
giql-0.1.3.dist-info/METADATA
giql-0.1.3.dist-info/WHEEL
giql-0.1.3.dist-info/entry_points.txt
giql-0.1.3.dist-info/RECORD
