Metadata-Version: 2.4
Name: giql
Version: 0.1.3
Summary: Genomic Interval Query Language - SQL dialect for genomic range queries
Author-email: Nezar Abdennur <nabdennur@gmail.com>, Conrad Bzura <conradbzura@gmail.com>
Maintainer-email: Nezar Abdennur <nabdennur@gmail.com>, Conrad Bzura <conradbzura@gmail.com>
Requires-Python: >=3.11
Requires-Dist: click>=8.3.0
Requires-Dist: duckdb>=1.4.0
Requires-Dist: oxbow>=0.4.0
Requires-Dist: pandas>=2.0.0
Requires-Dist: psycopg2-binary>=2.9.10
Requires-Dist: sqlglot>=20.0.0
Requires-Dist: sqlparse>=0.4.0
Provides-Extra: all
Requires-Dist: duckdb>=0.9.0; extra == 'all'
Requires-Dist: mysql-connector-python>=8.0.0; extra == 'all'
Requires-Dist: psycopg2-binary>=2.9.0; extra == 'all'
Provides-Extra: dev
Requires-Dist: hypothesis; extra == 'dev'
Requires-Dist: pybedtools; extra == 'dev'
Requires-Dist: pytest-cov>=4.0.0; extra == 'dev'
Requires-Dist: pytest>=7.0.0; extra == 'dev'
Requires-Dist: ruff>=0.1.0; extra == 'dev'
Provides-Extra: duckdb
Requires-Dist: duckdb>=0.9.0; extra == 'duckdb'
Provides-Extra: mysql
Requires-Dist: mysql-connector-python>=8.0.0; extra == 'mysql'
Provides-Extra: postgres
Requires-Dist: psycopg2-binary>=2.9.0; extra == 'postgres'
Provides-Extra: sqlite
